postgresql_integration_test/__init__.py
postgresql_integration_test/attributes.py
postgresql_integration_test/exceptions.py
postgresql_integration_test/helpers.py
postgresql_integration_test/log.py
postgresql_integration_test/postgresql.py
postgresql_integration_test/settings.py
postgresql_integration_test/version.py
postgresql_integration_test-0.0.4.dist-info/LICENSE
postgresql_integration_test-0.0.4.dist-info/METADATA
postgresql_integration_test-0.0.4.dist-info/WHEEL
postgresql_integration_test-0.0.4.dist-info/top_level.txt
postgresql_integration_test-0.0.4.dist-info/RECORD
