Metadata-Version: 2.1
Name: postgresql-integration-test
Version: 0.0.4
Summary: postgresql-integration-test is a python module that creates a temporary PostgreSQL instance to use for testing your application.
Author-email: Jason Camp <me@jason.camp>, Ian Meyer <k@imeyer.io>
License: Apache
Project-URL: Homepage, https://github.com/jasondcamp/postgresql-integration-test
Classifier: Development Status :: 3 - Alpha
Classifier: License :: OSI Approved :: Apache Software License
Classifier: Programming Language :: Python :: 3.7
Classifier: Programming Language :: Python :: 3.8
Classifier: Programming Language :: Python :: 3.9
Classifier: Programming Language :: Python :: 3.10
Classifier: Programming Language :: Python :: 3.11
Classifier: Programming Language :: Python :: 3.12
Requires-Python: >=3.7
License-File: LICENSE
Requires-Dist: psycopg2-binary >=2.9.9
Requires-Dist: pyyaml >=6.0.1
Provides-Extra: tests
Requires-Dist: pytest >=8.1.1 ; extra == 'tests'
Requires-Dist: pytest-env ==0.8.1 ; extra == 'tests'
Requires-Dist: pytest-cov ==4.0.0 ; extra == 'tests'
Requires-Dist: coverage >=7.2.1 ; extra == 'tests'
Requires-Dist: mock ==5.0.1 ; extra == 'tests'
Requires-Dist: pytest-mock ==3.10.0 ; extra == 'tests'
Requires-Dist: pytest-skip-slow ==0.0.5 ; extra == 'tests'
